dwiqc/__init__.py
dwiqc/__version__.py
dwiqc/browser/__init__.py
dwiqc/cli/__init__.py
dwiqc/cli/get.py
dwiqc/cli/install_containers.py
dwiqc/cli/process.py
dwiqc/cli/tandem.py
dwiqc/config/__init__.py
dwiqc/config/dwiqc.yaml
dwiqc/config/prequal.yaml
dwiqc/config/qsiprep.yaml
dwiqc/state/__init__.py
dwiqc/tasks/__init__.py
dwiqc/tasks/prequal.py
dwiqc/tasks/prequal_EQ.py
dwiqc/tasks/qsiprep.py
dwiqc/tasks/qsiprep_EQ.py
dwiqc/xnat/__init__.py
dwiqc-2.1.2.data/scripts/dwiQC.py
dwiqc-2.1.2.dist-info/LICENSE
dwiqc-2.1.2.dist-info/METADATA
dwiqc-2.1.2.dist-info/WHEEL
dwiqc-2.1.2.dist-info/top_level.txt
dwiqc-2.1.2.dist-info/RECORD
