Metadata-Version: 2.1
Name: dwiqc
Version: 2.1.2
Summary: Quality Assurance Pipeline for Diffusion MR Data
Home-page: https://github.com/harvard-nrg/dwiqc
Author: Neuroinformatics Research Group
Author-email: info@neuroinfo.org
License-File: LICENSE
Requires-Dist: yaxil==0.9.14
Requires-Dist: pyaml
Requires-Dist: xnattagger>=0.6.6
Requires-Dist: PyBIDS
Requires-Dist: executors==0.6a1
Requires-Dist: selfie
Requires-Dist: lxml
Requires-Dist: numpy==1.26.4
Requires-Dist: dcm2niix
Requires-Dist: tenacity
Requires-Dist: nibabel
Requires-Dist: dipy
